{
  "generated": "2026-06-23T21:15",
  "insiders": {},
  "funds": {
    "CIEN": [
      {"manager": "13F agregat (ok. 20 funduszy dolozylo ~1 mln akcji w Q1'26)", "pct_portfolio": 0, "action": "add"}
    ],
    "COHR": [
      {"manager": "WT Asset Management (+443%, ~520 mln USD, Q1'26)", "pct_portfolio": 1.5, "action": "add"}
    ]
  },
  "politicians": {},
  "sector_exits": [],
  "_notes": "Cykl 2026-06-23 (kandydaci: LITE, MU, CIEN, INTC, COHR). INSIDERZY (Form 4 / OpenInsider): brak SWIEZEGO (<=30 dni) KLASTRA ZAKUPOW na otwartym rynku dla zadnego z 5 -> fail-CLOSED, wszystkie NEUTRAL. MU: sprzedaze/grant, 0 open-market buy. LITE: sprzedaze, 0 kupna. CIEN: sprzedaze SVP/CSO 15.06 wg planu 10b5-1 - rutyna, NIE marker konwikcji. INTC: brak swiezych open-market buy (tylko upgrade BofA - to analityk, nie insider). COHR: brak swiezych Form 4 buy. FUNDUSZE (13F/Dataroma Q1'26 - migawka, bez zmiany d/d): CIEN bullish (ok.20 funduszy dolozylo ~1 mln akcji); COHR bullish (WT Asset Management +443.5%, ~520 mln USD). Zalogowane jako 'add'. POLITYCY (kongres): zakupy MU przez czlonkow Kongresu (Fetterman 30.03, Cisneros 25.03/24.02, Wied 19.02, Fields 03.02) oraz LITE (Cisneros 14.04, Gottheimer 22.05) - WSZYSTKIE POZA oknem <=7 dni (>30 dni temu) -> pomijam (fail-CLOSED). KONKLUZJA: jedyne pozytywne sygnaly smart-money to 13F CIEN i COHR (warstwa funduszy, Q1 snapshot, opozniona); insiderzy i politycy neutralni."
}
